overlincs_git/__init__.py
overlincs_git/admin.py
overlincs_git/cli.py
overlincs_git-0.1.0.dist-info/LICENSE
overlincs_git-0.1.0.dist-info/METADATA
overlincs_git-0.1.0.dist-info/WHEEL
overlincs_git-0.1.0.dist-info/entry_points.txt
overlincs_git-0.1.0.dist-info/RECORD
