Metadata-Version: 2.1
Name: overlincs-git
Version: 0.1.0
Summary: Unofficial fork of python-sharelatex to manage overleaf.lincs.fr
Home-page: https://github.com/balouf/overlincs-git
Author: Fabien Mathieu
Author-email: loufab@gmail.com
Requires-Python: >=3.9,<4.0
Classifier: Programming Language :: Python :: 3
Classifier: Programming Language :: Python :: 3.9
Classifier: Programming Language :: Python :: 3.10
Classifier: Programming Language :: Python :: 3.11
Classifier: Programming Language :: Python :: 3.12
Requires-Dist: appdirs (>=1.4.4,<2.0.0)
Requires-Dist: click (>=8.1.7,<9.0.0)
Requires-Dist: filetype (>=1.2.0,<2.0.0)
Requires-Dist: gitpython (>=3.1.40,<4.0.0)
Requires-Dist: keyring (>=24.3.0,<25.0.0)
Requires-Dist: lxml (>=4.9.3,<5.0.0)
Requires-Dist: pymongo (>=4.6.1,<5.0.0)
Requires-Dist: python-dateutil (>=2.8.2,<3.0.0)
Requires-Dist: socketio-client (==0.5.7.4)
Project-URL: Documentation, https://balouf.github.io/overlincs-git
Project-URL: Repository, https://github.com/balouf/overlincs-git
